{
  "schema_version": "1.0.0",
  "id": "elasticsearch/nested-doc-limit/es8-linux",
  "url": "https://deadends.dev/elasticsearch/nested-doc-limit/es8-linux",
  "error": {
    "signature": "IllegalArgumentException: number of nested documents exceeds limit",
    "regex": "(nested documents.*limit|nested.*exceeded|too many nested)",
    "domain": "elasticsearch",
    "category": "config_error",
    "first_seen": "2023-01-01",
    "last_confirmed": "2026-02-26"
  },
  "environment": {
    "runtime": {
      "name": "elasticsearch",
      "version_range": ">=8.0"
    },
    "os": "linux"
  },
  "verdict": {
    "resolvable": "true",
    "fix_success_rate": 0.8,
    "confidence": 0.84,
    "last_updated": "2026-02-26",
    "summary": "Document contains too many nested objects."
  },
  "dead_ends": [
    {
      "action": "Increase nested limit to millions",
      "why_fails": "Massive memory usage per document",
      "fail_rate": 0.82,
      "sources": [],
      "condition": ""
    },
    {
      "action": "Flatten all nested objects",
      "why_fails": "Loses nested query capability",
      "fail_rate": 0.75,
      "sources": [],
      "condition": ""
    }
  ],
  "workarounds": [
    {
      "action": "Redesign data model: use parent-child or denormalized structure",
      "success_rate": 0.88,
      "sources": [],
      "condition": ""
    },
    {
      "action": "Increase limit moderately: index.mapping.nested_objects.limit",
      "success_rate": 0.85,
      "sources": [],
      "condition": ""
    }
  ],
  "transition_graph": {
    "leads_to": [],
    "preceded_by": [],
    "frequently_confused_with": []
  },
  "metadata": {
    "generated_by": "bulk_generate.py",
    "generation_date": "2026-02-26",
    "review_status": "auto_generated",
    "evidence_count": 3,
    "last_verification": "2026-02-26"
  }
}