{
  "schema_version": "1.0.0",
  "id": "python/timeouterror/py311-linux",
  "url": "https://deadends.dev/python/timeouterror/py311-linux",
  "error": {
    "signature": "TimeoutError: [Errno 110] Connection timed out",
    "regex": "TimeoutError|timed? ?out",
    "domain": "python",
    "category": "network_error",
    "first_seen": "2023-01-01",
    "last_confirmed": "2026-02-11"
  },
  "environment": {
    "runtime": {
      "name": "python",
      "version_range": ">=3.11,<3.13"
    },
    "os": "linux",
    "python": ">=3.11,<3.13"
  },
  "verdict": {
    "resolvable": "true",
    "fix_success_rate": 0.8,
    "confidence": 0.82,
    "last_updated": "2026-02-11",
    "summary": "Network connection or operation timed out."
  },
  "dead_ends": [
    {
      "action": "Increase timeout to very large value",
      "why_fails": "Just delays the failure, doesn't fix the network issue",
      "fail_rate": 0.65,
      "sources": [
        "https://docs.python.org/3/library/socket.html#socket.settimeout"
      ],
      "condition": ""
    },
    {
      "action": "Remove timeout entirely",
      "why_fails": "Process hangs forever on unreachable hosts",
      "fail_rate": 0.85,
      "sources": [
        "https://docs.python.org/3/library/socket.html"
      ],
      "condition": ""
    }
  ],
  "workarounds": [
    {
      "action": "Add retry with exponential backoff for transient failures",
      "success_rate": 0.9,
      "sources": [
        "https://docs.python.org/3/library/urllib.request.html"
      ],
      "condition": "",
      "how": ""
    },
    {
      "action": "Verify target host is reachable: DNS, firewall, port",
      "success_rate": 0.88,
      "sources": [
        "https://docs.python.org/3/library/socket.html#socket.create_connection"
      ],
      "condition": "",
      "how": "DNS, firewall, port"
    }
  ],
  "transition_graph": {
    "leads_to": [],
    "preceded_by": [],
    "frequently_confused_with": []
  },
  "metadata": {
    "generated_by": "bulk_generate.py",
    "generation_date": "2026-02-11",
    "review_status": "auto_generated",
    "evidence_count": 50,
    "last_verification": "2026-02-11"
  }
}
