{
  "schema_version": "1.0.0",
  "id": "typescript/ts2454-variable-used-before-assigned/ts5-linux",
  "url": "https://deadends.dev/typescript/ts2454-variable-used-before-assigned/ts5-linux",
  "error": {
    "signature": "error TS2454: Variable 'x' is used before being assigned",
    "regex": "TS2454.*used before being assigned",
    "domain": "typescript",
    "category": "type_error",
    "first_seen": "2023-01-01",
    "last_confirmed": "2026-02-11"
  },
  "environment": {
    "runtime": {
      "name": "typescript",
      "version_range": ">=5.0,<6.0"
    },
    "os": "linux"
  },
  "verdict": {
    "resolvable": "true",
    "fix_success_rate": 0.95,
    "confidence": 0.95,
    "last_updated": "2026-02-11",
    "summary": "Variable accessed before all code paths assign it. TypeScript flow analysis detected a gap."
  },
  "dead_ends": [
    {
      "action": "Use ! non-null assertion: x!",
      "why_fails": "May cause runtime undefined access if the analysis is correct",
      "fail_rate": 0.65,
      "sources": [
        "https://www.typescriptlang.org/docs/handbook/2/narrowing.html"
      ],
      "condition": ""
    }
  ],
  "workarounds": [
    {
      "action": "Initialize the variable at declaration: let x: Type = defaultValue",
      "success_rate": 0.95,
      "sources": [
        "https://www.typescriptlang.org/docs/handbook/2/narrowing.html"
      ],
      "condition": "",
      "how": "let x: Type = defaultValue"
    },
    {
      "action": "Restructure code so all branches assign before use",
      "success_rate": 0.9,
      "sources": [
        "https://www.typescriptlang.org/docs/handbook/2/narrowing.html"
      ],
      "condition": "",
      "how": "// Ensure all branches assign the variable:\nlet result: string;\nif (condition) {\n  result = 'yes';\n} else {\n  result = 'no'; // must assign in every branch\n}\nconsole.log(result); // now guaranteed to be assigned\n\n// Or initialize with a default:\nlet result: string = 'default';"
    }
  ],
  "transition_graph": {
    "leads_to": [
      {
        "error_id": "typescript/ts2322-type-not-assignable/ts5-linux",
        "probability": 0.18
      }
    ],
    "preceded_by": [],
    "frequently_confused_with": [
      {
        "error_id": "typescript/ts2345-argument-not-assignable/ts5-linux",
        "distinction": "'TS2454' indicates a variable used before assignment, while 'TS2345' indicates an argument type mismatch."
      },
      {
        "error_id": "typescript/ts2352-conversion-may-be-mistake/ts5-linux",
        "distinction": "'TS2454' indicates a variable used before assignment, while 'TS2352' indicates a potentially incorrect type conversion."
      }
    ]
  },
  "metadata": {
    "generated_by": "bulk_generate.py",
    "generation_date": "2026-02-11",
    "review_status": "auto_generated",
    "evidence_count": 50,
    "last_verification": "2026-02-11"
  }
}
