{
  "schema_version": "1.0.0",
  "id": "embedded/hardfault-handler/stm32-arm-linux",
  "url": "https://deadends.dev/embedded/hardfault-handler/stm32-arm-linux",
  "error": {
    "signature": "HardFault_Handler: FORCED, bus fault at address 0x00000000",
    "regex": "(HardFault|Hard[_ ]?[Ff]ault|BusFault|MemManage|UsageFault|FORCED.*fault)",
    "domain": "embedded",
    "category": "runtime_error",
    "first_seen": "2023-01-01",
    "last_confirmed": "2026-02-23"
  },
  "environment": {
    "runtime": {
      "name": "stm32",
      "version_range": ">=F1"
    },
    "os": "cross-platform",
    "additional": {
      "architecture": "arm"
    }
  },
  "verdict": {
    "resolvable": "partial",
    "fix_success_rate": 0.55,
    "confidence": 0.85,
    "last_updated": "2026-02-23",
    "summary": "ARM Cortex-M hard fault. Null pointer, stack overflow, unaligned access, or invalid memory."
  },
  "dead_ends": [
    {
      "action": "Add while(1) in HardFault handler and inspect PC in debugger",
      "why_fails": "PC in handler points to handler itself, not faulting instruction. Read stacked PC from exception frame.",
      "fail_rate": 0.72,
      "sources": [
        "https://www.st.com/resource/en/reference_manual/"
      ],
      "condition": ""
    },
    {
      "action": "Increase heap size assuming memory allocation failure",
      "why_fails": "Hard faults are usually stack overflow or dangling pointers. Heap failures return NULL.",
      "fail_rate": 0.78,
      "sources": [
        "https://www.st.com/resource/en/reference_manual/"
      ],
      "condition": ""
    },
    {
      "action": "Disable fault handlers to prevent stopping",
      "why_fails": "Without handlers, faults escalate to lockup; processor halts until hardware reset",
      "fail_rate": 0.92,
      "sources": [
        "https://www.st.com/resource/en/reference_manual/"
      ],
      "condition": ""
    }
  ],
  "workarounds": [
    {
      "action": "Read stacked PC/LR from exception frame to find faulting instruction",
      "success_rate": 0.85,
      "how": "In handler: read SP, stacked_pc = *(SP+24), look up in .map file",
      "sources": [],
      "condition": ""
    },
    {
      "action": "Enable BusFault, MemManage, UsageFault handlers for specific info",
      "success_rate": 0.88,
      "how": "SCB->SHCSR |= (BUSFAULTENA | MEMFAULTENA | USGFAULTENA);",
      "sources": [],
      "condition": ""
    },
    {
      "action": "Check stack size and add overflow detection",
      "success_rate": 0.8,
      "how": "FreeRTOS: configCHECK_FOR_STACK_OVERFLOW=2; Bare metal: fill stack with 0xDEADBEEF",
      "sources": [],
      "condition": ""
    }
  ],
  "transition_graph": {
    "leads_to": [],
    "preceded_by": [],
    "frequently_confused_with": []
  },
  "metadata": {
    "generated_by": "bulk_generate.py",
    "generation_date": "2026-02-23",
    "review_status": "auto_generated",
    "evidence_count": 3,
    "last_verification": "2026-02-23"
  }
}
