{
  "schema_version": "1.0.0",
  "id": "ros2/image-transport-plugin-not-found/ros2-humble-linux",
  "url": "https://deadends.dev/ros2/image-transport-plugin-not-found/ros2-humble-linux",
  "error": {
    "signature": "image_transport: No plugin found for transport 'compressed'",
    "regex": "(image_transport.*plugin.*not found|transport.*compressed.*not.*available|image_transport.*No.*plugin|compressed.*transport.*missing)",
    "domain": "ros2",
    "category": "runtime_error",
    "first_seen": "2023-01-01",
    "last_confirmed": "2026-02-24"
  },
  "environment": {
    "runtime": {
      "name": "ros2",
      "version_range": ">=humble,<rolling"
    },
    "os": "linux"
  },
  "verdict": {
    "resolvable": "true",
    "fix_success_rate": 0.92,
    "confidence": 0.9,
    "last_updated": "2026-02-24",
    "summary": "image_transport cannot find the compressed/theora/raw transport plugin. Missing package installation."
  },
  "dead_ends": [
    {
      "action": "Manually compress images in the subscriber callback",
      "why_fails": "Bypasses image_transport entirely; loses bandwidth-efficient transport and standard interface",
      "fail_rate": 0.8,
      "sources": [],
      "condition": ""
    },
    {
      "action": "Use raw transport and accept the bandwidth cost",
      "why_fails": "Raw HD images over WiFi or limited bandwidth saturate the link; drops frames",
      "fail_rate": 0.7,
      "sources": [],
      "condition": ""
    }
  ],
  "workarounds": [
    {
      "action": "Install image_transport plugins package",
      "success_rate": 0.95,
      "how": "sudo apt install ros-humble-image-transport-plugins",
      "sources": [],
      "condition": ""
    },
    {
      "action": "Verify available transports with ros2 run image_transport list_transports",
      "success_rate": 0.88,
      "how": "ros2 run image_transport list_transports",
      "sources": [],
      "condition": ""
    },
    {
      "action": "Re-source workspace after installing new transport plugins",
      "success_rate": 0.85,
      "sources": [],
      "condition": ""
    }
  ],
  "transition_graph": {
    "leads_to": [],
    "preceded_by": [],
    "frequently_confused_with": []
  },
  "metadata": {
    "generated_by": "bulk_generate.py",
    "generation_date": "2026-02-24",
    "review_status": "auto_generated",
    "evidence_count": 50,
    "last_verification": "2026-02-24"
  }
}
