{
  "schema_version": "1.0.0",
  "id": "cloud/gcp-metadata-server-timeout/gcp-compute-any",
  "url": "https://deadends.dev/cloud/gcp-metadata-server-timeout/gcp-compute-any",
  "error": {
    "signature": "metadata.google.internal timeout — GCP metadata server unreachable",
    "regex": "metadata\\.google\\.internal.*timeout|169\\.254\\.169\\.254.*timeout",
    "domain": "cloud",
    "category": "metadata",
    "first_seen": "2023-01-01",
    "last_confirmed": "2026-02-25"
  },
  "environment": {
    "runtime": {
      "name": "GCP Compute",
      "version_range": ">=any"
    },
    "os": "linux"
  },
  "verdict": {
    "resolvable": "true",
    "fix_success_rate": 0.82,
    "confidence": 0.85,
    "last_updated": "2026-02-25",
    "summary": "GCP metadata server becomes temporarily unreachable during high network load."
  },
  "dead_ends": [
    {
      "action": "Add metadata.google.internal to /etc/hosts",
      "why_fails": "The IP is already 169.254.169.254; hosts file does not fix network-level issues",
      "fail_rate": 0.75,
      "sources": [
        "https://cloud.google.com/compute/docs/metadata/overview"
      ],
      "condition": ""
    },
    {
      "action": "Increase HTTP client timeout to 60s",
      "why_fails": "Longer timeout alone does not help; need retry logic",
      "fail_rate": 0.65,
      "sources": [
        "https://cloud.google.com/compute/docs/metadata/overview"
      ],
      "condition": ""
    }
  ],
  "workarounds": [
    {
      "action": "Implement retry with exponential backoff on metadata requests",
      "success_rate": 0.9,
      "how": "for i in range(5): try: return requests.get(url, timeout=5) except: time.sleep(2**i)",
      "sources": [
        "https://cloud.google.com/compute/docs/metadata/overview"
      ],
      "condition": ""
    },
    {
      "action": "Use Metadata-Flavor: Google header and retry on 503",
      "success_rate": 0.88,
      "how": "headers={'Metadata-Flavor': 'Google'}",
      "sources": [
        "https://cloud.google.com/compute/docs/metadata/querying-metadata"
      ],
      "condition": ""
    }
  ],
  "transition_graph": {
    "leads_to": [],
    "preceded_by": [],
    "frequently_confused_with": []
  },
  "metadata": {
    "generated_by": "bulk_generate.py",
    "generation_date": "2026-02-25",
    "review_status": "auto_generated",
    "evidence_count": 4,
    "last_verification": "2026-02-25"
  }
}
